quantacore/__init__.py
quantacore/_ffi.py
quantacore/_native.py
quantacore/device.py
quantacore/exceptions.py
quantacore/hash.py
quantacore/kem.py
quantacore/keys.py
quantacore/library.py
quantacore/py.typed
quantacore/random.py
quantacore/sign.py
quantacore/types.py
quantacore/utils.py
quantacore/native/__init__.py
quantacore_sdk-1.0.1.dist-info/LICENSE
quantacore_sdk-1.0.1.dist-info/METADATA
quantacore_sdk-1.0.1.dist-info/WHEEL
quantacore_sdk-1.0.1.dist-info/top_level.txt
quantacore_sdk-1.0.1.dist-info/RECORD
