Metadata-Version: 2.1
Name: quantacore-sdk
Version: 1.0.1
Summary: Python bindings for the QUAC 100 Post-Quantum Cryptographic Accelerator
Home-page: https://github.com/dyber-pqc/quantacore-sdk
Author: Dyber, Inc.
Author-email: "Dyber, Inc." <support@dyber.org>
Maintainer-email: "Dyber, Inc." <support@dyber.org>
Project-URL: Homepage, https://dyber.org
Project-URL: Documentation, https://docs.dyber.org/quac100/python
Project-URL: Repository, https://github.com/dyber-pqc/quantacore-sdk
Project-URL: Issues, https://github.com/dyber-pqc/quantacore-sdk/issues
Keywords: cryptography,post-quantum,pqc,kyber,dilithium,ml-kem,ml-dsa,hardware-security,hsm,qrng,quac100
Classifier: Development Status :: 4 - Beta
Classifier: Intended Audience :: Developers
Classifier: Intended Audience :: Science/Research
Classifier: Operating System :: Microsoft :: Windows
Classifier: Operating System :: POSIX :: Linux
Classifier: Operating System :: MacOS :: MacOS X
Classifier: Programming Language :: Python :: 3
Classifier: Programming Language :: Python :: 3.8
Classifier: Programming Language :: Python :: 3.9
Classifier: Programming Language :: Python :: 3.10
Classifier: Programming Language :: Python :: 3.11
Classifier: Programming Language :: Python :: 3.12
Classifier: Topic :: Security :: Cryptography
Classifier: Topic :: Software Development :: Libraries :: Python Modules
Classifier: Typing :: Typed
Requires-Python: >=3.8
License-File: LICENSE
Provides-Extra: dev
Requires-Dist: pytest>=7.0; extra == "dev"
Requires-Dist: pytest-cov>=4.0; extra == "dev"
Requires-Dist: mypy>=1.0; extra == "dev"
Requires-Dist: black>=23.0; extra == "dev"
Requires-Dist: isort>=5.0; extra == "dev"
Requires-Dist: flake8>=6.0; extra == "dev"
Requires-Dist: sphinx>=6.0; extra == "dev"
Requires-Dist: sphinx-rtd-theme>=1.0; extra == "dev"
Provides-Extra: docs
Requires-Dist: sphinx>=6.0; extra == "docs"
Requires-Dist: sphinx-rtd-theme>=1.0; extra == "docs"
Provides-Extra: test
Requires-Dist: pytest>=7.0; extra == "test"
Requires-Dist: pytest-cov>=4.0; extra == "test"
